notion2pg.py
notion2pg-0.1.0.dist-info/entry_points.txt
notion2pg-0.1.0.dist-info/LICENSE
notion2pg-0.1.0.dist-info/WHEEL
notion2pg-0.1.0.dist-info/METADATA
notion2pg-0.1.0.dist-info/RECORD
