Metadata-Version: 2.1
Name: notion2pg
Version: 0.1.0
Summary: Import Notion databases to PostgreSQL tables
Home-page: https://github.com/aaugustin/notion2pg
License: BSD-3-Clause
Keywords: notion,postgresql
Author: Aymeric Augustin
Author-email: aymeric.augustin@fractalideas.com
Requires-Python: >=3.8,<4.0
Classifier: Development Status :: 3 - Alpha
Classifier: License :: OSI Approved :: BSD License
Classifier: Operating System :: OS Independent
Classifier: Programming Language :: Python :: 3
Classifier: Programming Language :: Python :: 3.10
Classifier: Programming Language :: Python :: 3.8
Classifier: Programming Language :: Python :: 3.9
Requires-Dist: httpx
Requires-Dist: psycopg
Project-URL: Repository, https://github.com/aaugustin/notion2pg
